{
    "textures" : [
        { "id" : "assets/bullet.png" },
        { "id" : "assets/blood.png" },
		{ "id" : "assets/enemy.png" },
		{ "id" : "assets/player.png" },
		{ "id" : "assets/rock.png" },
		{ "id" : "assets/rock-shadow.png"},
		{ "id" : "assets/tileset.png" },
        { "id" : "assets/weapon.png" },
        { "id" : "assets/powerup_crit.png" },
        { "id" : "assets/powerup_firerate.png" },
        { "id" : "assets/healthbar.png" },
		{ "id" : "assets/eye.png" },
    ],
    "fonts" : [
    ],
    "sounds" : [
        { "id" : "assets/35451__inkington__hit-mic06.wav", "name" : "hit", "is_stream" : true },
        { "id" : "assets/161862__antistatikk__balloon-bass-12.wav", "name" : "boom", "is_stream" : true },
        { "id" : "assets/bite-small.wav", "name" : "bite", "is_stream" : true },
        { "id" : "assets/bite-small2.wav", "name" : "bite2", "is_stream" : true },
        { "id" : "assets/bite-small3.wav", "name" : "bite3", "is_stream" : true },
    ]
}